CHANGES.txt
LICENSE.txt
README.txt
setup.py
js/__init__.py
js.jqueryui_syronex_colorpicker.egg-info/PKG-INFO
js.jqueryui_syronex_colorpicker.egg-info/SOURCES.txt
js.jqueryui_syronex_colorpicker.egg-info/dependency_links.txt
js.jqueryui_syronex_colorpicker.egg-info/entry_points.txt
js.jqueryui_syronex_colorpicker.egg-info/namespace_packages.txt
js.jqueryui_syronex_colorpicker.egg-info/not-zip-safe
js.jqueryui_syronex_colorpicker.egg-info/requires.txt
js.jqueryui_syronex_colorpicker.egg-info/top_level.txt
js/jqueryui_syronex_colorpicker/__init__.py
js/jqueryui_syronex_colorpicker/resources/README.txt
js/jqueryui_syronex_colorpicker/resources/license.txt
js/jqueryui_syronex_colorpicker/resources/syronex-colorpicker.css
js/jqueryui_syronex_colorpicker/resources/syronex-colorpicker.gif
js/jqueryui_syronex_colorpicker/resources/syronex-colorpicker.js