Metadata-Version: 1.0
Name: js.jqueryui_syronex_colorpicker
Version: 1.0.0
Summary: Fanstatic packaging of syronex_colorpicker
Home-page: http://github.com/do3cc/js.jqueryui_syronex_colorpicker
Author: Fanstatic Developers
Author-email: fanstatic@googlegroups.com
License: UNKNOWN
Platform: UNKNOWN
